{
  "hash": "5af2a501b2b73155b5b73b0cb817e2d5",
  "result": {
    "engine": "knitr",
    "markdown": "::: {.question}\n\n**Informed vs. Fad Followers vs. Passive: Who Earns Alpha?**\n\n\n\n```\nWarning: package 'knitr' was built under R version 4.2.3\n```\n\n\nIn a market with **74% passive**, **4% informed**, and **22% fad followers**, the informed trade a portfolio with **β = 1.63** and **E[R] = 17%**.  \nGiven **R<sub>f</sub> = 4%**, **E[R<sub>m</sub>] = 9%** (**MRP = 5%**):\n\n::: {.question-block}\n<form onsubmit=\"event.preventDefault();\" style=\"display:flex; gap:8px; align-items:center;\">\n  <label for=\"module5_num_q2a\"><strong>2a. Informed investors’ alpha (bp):</strong></label>\n  <input type=\"number\" id=\"module5_num_q2a\" name=\"module5_num_q2a\" style=\"width:180px;\"\n         data-correct-answer=485 data-tolerance=\"1\" step=\"1\" />\n</form>\n\n<div id=\"feedback-module5_num_q2a\" class=\"feedback\" data-status=\"\" style=\"display:none;\">\n✅ <strong>Informed α</strong><br>\nCAPM prediction = R<sub>f</sub> + β(R<sub>m</sub> − R<sub>f</sub>) = \n12.15%.<br>\nObserved E[R] = 17%.<br>\nα<sub>informed</sub> = E[R] − CAPM = 17% − 12.15% = \n<strong>485 bp</strong>.\n</div>\n:::\n\n::: {.question-block}\n<form onsubmit=\"event.preventDefault();\" style=\"display:flex; gap:8px; align-items:center; flex-wrap:wrap;\">\n  <label for=\"module5_num_q2b\"><strong>2b. Fad followers’ expected return (in %):</strong></label>\n  <input type=\"number\" id=\"module5_num_q2b\" name=\"module5_num_q2b\" style=\"width:200px;\"\n         data-correct-answer=-8 data-tolerance=\"0.05\" step=\"0.01\" />\n</form>\n\n<div id=\"feedback-module5_num_q2b\" class=\"feedback\" data-status=\"\" style=\"display:none;\">\n✅ <strong>Fad followers’ E[R]</strong><br>\nWithin the <em>trading segment</em> (informed + fad), expected return must match the CAPM prediction for the counterparty exposure:<br>\nE[R]<sub>traded</sub> (CAPM) = R<sub>f</sub> − β(R<sub>m</sub> − R<sub>f</sub>) = <strong>-4.15%</strong>.<br>\nLet weights inside the trading segment be w<sub>I</sub>=15% and w<sub>F</sub>=85%. Then:<br>\nw<sub>I</sub>E[R]<sub>I</sub> + w<sub>F</sub>E[R]<sub>F</sub> = E[R]<sub>traded</sub> ⇒ \nE[R]<sub>F</sub> = (E[R]<sub>traded</sub> − w<sub>I</sub>E[R]<sub>I</sub>)/w<sub>F</sub> = \n<strong>-8%</strong>.\n</div>\n:::\n\n::: {.question-block}\n<form onsubmit=\"event.preventDefault();\" style=\"display:flex; gap:8px; align-items:center;\">\n  <label for=\"module5_num_q2c\"><strong>2c. Fad followers’ alpha (bp) <em>(vs CAPM with β of informed)</em>:</strong></label>\n  <input type=\"number\" id=\"module5_num_q2c\" name=\"module5_num_q2c\" style=\"width:240px;\"\n         data-correct-answer=-2014.5 data-tolerance=\"1\" step=\"1\" />\n</form>\n\n<div id=\"feedback-module5_num_q2c\" class=\"feedback\" data-status=\"\" style=\"display:none;\">\n✅ <strong>Fad followers’ α</strong><br>\nWe evaluate α against the same β used by the informed portfolio (as in the textbook exercise). CAPM benchmark = <strong>12.15%</strong>.<br>\nE[R]<sub>F</sub> = <strong>-8%</strong> ⇒ α<sub>F</sub> = E[R]<sub>F</sub> − CAPM = \n<strong>-2014.5 bp</strong>.<br>\nInterpretation: informed earn positive α (skill), the <em>counterparty</em> earns negative α; the passive investor (market) earns zero α.\n</div>\n:::\n\n\n:::\n",
    "supporting": [],
    "filters": [
      "rmarkdown/pagebreak.lua"
    ],
    "includes": {},
    "engineDependencies": {},
    "preserve": {},
    "postProcess": true
  }
}