{
  "hash": "4bbc6550f7477cd3e5d5da65b23970fa",
  "result": {
    "engine": "knitr",
    "markdown": "---\ntitle: \"Part 3 (ch11) Questions Numeric\"\n---\n\n\n::: {style=\"display: flex; justify-content: space-between; width: 100%;\"}\n[Go to previous chapter](p2num.qmd){.btn .btn-primary role=\"button\" data-toggle=\"tool\" style=\"margin-right: 430px;\"}\n[Go to next chapter](p4num.qmd){.btn .btn-primary role=\"button\" data-toggle=\"tool\"}\n:::\n\n\n::: {.callout-note}\n### For students\n\n**Last updated: 31/01/2025  **\n\n**Type your answers with \".\" instead of \",\"! For numerical answers, use 2 decimal places. For instance, if your answer is 0.12345 or 12.345%, type, \"12.34\" in the box.**\n\n:::\n\n\n\n## Question 1\n\n\n\n\n\n\n**Q:** What is the **expected return** of a portfolio that invests 0.429 percent in Asset 1 (expected return = -0.009)  and the remaining 0.571 in Asset 2 (expected return = -0.09)? \n\n<input class='webex-solveme nospaces' data-tol='0.01' size='6' data-answer='[\"-5.543\"]'/>\n\n\n**Q:** Assuming that the correlation between these assets is 0.388, and that the standard deviation of Asset 1 is 0.243 while the standard deviation of Asset 2 is 0.17, what is the **variance** of the portfolio above?\n\n<input class='webex-solveme nospaces' data-tol='0.01' size='5' data-answer='[\"2.812\"]'/>\n\n\n\n**Q:** Assuming that the correlation between these assets is 0.388, and that the standard deviation of Asset 1 is 0.243 while the standard deviation of Asset 2 is 0.17, what is the **standard deviation** of the portfolio above?\n\n<input class='webex-solveme nospaces' data-tol='0.01' size='6' data-answer='[\"16.768\"]'/>\n\n\n___\n\n\n**Answer**\n\n1) -5.543\n\n2) 2.812\n\n3) 16.768\n\n\n\n\n\n\n___\n\n\n<script src=\"https://giscus.app/client.js\"\n        data-repo=\"henriquecastror/EF_permanent\"\n        data-repo-id=\"R_kgDOLMIejg\"\n        data-category=\"General\"\n        data-category-id=\"DIC_kwDOLMIejs4Cc1yS\"\n        data-mapping=\"number\"\n        data-term=\"6\"\n        data-reactions-enabled=\"1\"\n        data-emit-metadata=\"0\"\n        data-input-position=\"bottom\"\n        data-theme=\"light\"\n        data-lang=\"en\"\n        crossorigin=\"anonymous\"\n        async>\n</script>\n\n\n::: {style=\"display: flex; justify-content: space-between; width: 100%;\"}\n[Go to previous chapter](p2num.qmd){.btn .btn-primary role=\"button\" data-toggle=\"tool\" style=\"margin-right: 430px;\"}\n[Go to next chapter](p4num.qmd){.btn .btn-primary role=\"button\" data-toggle=\"tool\"}\n:::\n",
    "supporting": [],
    "filters": [
      "rmarkdown/pagebreak.lua"
    ],
    "includes": {},
    "engineDependencies": {},
    "preserve": {},
    "postProcess": true
  }
}