{
  "hash": "881a0425debfa9e05d9a8b97dcf03210",
  "result": {
    "engine": "knitr",
    "markdown": "\n\n\nAn institutional investor holds two divisions of Aurora Technologies:  \n- Division A weight = **57.52**%, beta = **1.33**  \n- Division B weight = **42.48**%, beta = **0.74**  \n\n::: {.question-block}\n<form onsubmit=\"event.preventDefault();\" style=\"display: flex; flex-direction: row; gap: 6px;\">\n  <label for=\"module4_num_q8a\"><strong>1. What is the overall portfolio beta?</strong></label>\n  <input type=\"number\" id=\"module4_num_q8a\" name=\"module4_num_q8a\" style=\"width: 150px;\"\n         data-correct-answer=1.08 data-tolerance=\"0.01\" />\n</form>\n\n<div id=\"feedback-module4_num_q8a\" class=\"feedback\" style=\"display:none;\">\n✅ Portfolio Beta = w<sub>A</sub>β<sub>A</sub> + w<sub>B</sub>β<sub>B</sub> = **1.08**.  \nThis shows how different risk exposures combine in a weighted portfolio.\n</div>\n:::\n",
    "supporting": [],
    "filters": [
      "rmarkdown/pagebreak.lua"
    ],
    "includes": {},
    "engineDependencies": {},
    "preserve": {},
    "postProcess": true
  }
}